pycvtools.py
pycvtools-0.0.4.dist-info/LICENSE
pycvtools-0.0.4.dist-info/METADATA
pycvtools-0.0.4.dist-info/WHEEL
pycvtools-0.0.4.dist-info/top_level.txt
pycvtools-0.0.4.dist-info/RECORD
