Metadata-Version: 2.1
Name: pycvtools
Version: 0.0.4
Summary: A package to take for preprocessing the images and video.
Home-page: https://www.drateendrajha.com/projects/pycvtools
Author: Ateendra Jha
Author-email: ateendrajha@live.com
License: UNKNOWN
Keywords: video,images,video2images,image crop
Platform: UNKNOWN
Classifier: Programming Language :: Python :: 3
Classifier: License :: OSI Approved :: MIT License
Classifier: Operating System :: OS Independent
Requires-Python: >=3.6
License-File: LICENSE
Requires-Dist: opencv-python
Requires-Dist: numpy
Requires-Dist: tensorflow
Requires-Dist: pillow
